<?xml version="1.0" encoding="UTF-8"?>
<metadata>
  <identifier>scgmd</identifier>
  <mediatype>software</mediatype>
  <collection>flasharchive</collection>
  <creator>Shinki</creator>
  <description>Super Crazy Guitar Maniac Deluxe is a series of flash games by Shinki. The games are similar to Guitar Hero in term of gameplay. The player must press the correct key when i reaches to the center without breaking the combo.</description>
  <scanner>Internet Archive HTML5 Uploader 1.6.4</scanner>
  <subject>flash</subject>
  <subject>guitar</subject>
  <title>Super Crazy Guitar Maniac Deluxe</title>
  <uploader>lyons.jimmy97@yahoo.com</uploader>
  <publicdate>2020-03-02 00:10:04</publicdate>
  <addeddate>2020-03-02 00:10:04</addeddate>
  <curation>[curator]validator@archive.org[/curator][date]20200302001743[/date][comment]checked for malware[/comment]</curation>
  <backup_location>ia907106_17</backup_location>
</metadata>
